{"1OJsz6crW7BO5kQg+FST9g==":"mbr-206x121.png","dsmEumzvM62+pWswJdB75g==":"mbr-646x431.jpg","CbgJTVWrmHB6cPMhVtX4dg==":"mbr-1-646x431.jpg","Iwn/j5dgaLfO61rmZjsHzQ==":"mbr-646x363.jpg","sKHQHDhVGibXf9DYYbD4Bg==":"mbr-646x515.jpg","pLbAES1DoKhFgR+Fk4zBmg==":"mbr-1357x903.jpg","GEnJMovLEApxmFtG3f4xPg==":"mbr-1357x905.jpg","Qy/tasSjmC12bZxhHbIDig==":"1%20(1)-921x921.jpg","AkwK3jnAMxsUjwKJilHXQg==":"1%20(3)-921x921.jpg","TxHI5KGlrG26Y2kUb3h3Sg==":"1%20(5)-921x921.jpg","yCqdc4QqFyn/rdF9BTJ2HQ==":"1%20(4)-921x921.jpg","RfE9ZVKDKbzJm1eVJ+GnFA==":"1-646x819.png","cy+0qF1MgR612Na65U0vcQ==":"2-883x596.png","SnTxI+8th6VItBLKsxp59g==":"5-883x684.png","QnlfkuAzXW4vxXhYSFJk8g==":"5-1-883x684.png","VXxmVYWiQbPSE8enJnUzAA==":"6-883x1138.png","fbBuj9KQ5ieu1rSFiy+v0Q==":"3-883x773.png","eJQd7BgAPmJ8bKCM6VAp0w==":"a2-646x861.jpg","FDpRNhv/Nh7cJiG5Lnq8bQ==":"a3-646x1175.jpg","7216XCDOpP0QwxXF8S2izQ==":"a1-646x556.jpg","h8O26knyFlqNiq7gFdWfaw==":"a4-646x377.jpg"}